README.rst
pytest_runfailed.py
setup.py
pytest_runfailed.egg-info/PKG-INFO
pytest_runfailed.egg-info/SOURCES.txt
pytest_runfailed.egg-info/dependency_links.txt
pytest_runfailed.egg-info/entry_points.txt
pytest_runfailed.egg-info/pbr.json
pytest_runfailed.egg-info/requires.txt
pytest_runfailed.egg-info/top_level.txt