Metadata-Version: 1.1
Name: pytest-runfailed
Version: 0.5
Summary: implement a --failed option for pytest
Home-page: http://github.com/dmerejkowsky/pytest-runfailed
Author: Dimitri Merejkowsky
Author-email: d.merej@gmail.com
License: BSD
Platform: UNKNOWN
Classifier: Topic :: Software Development :: Testing
Classifier: Intended Audience :: Developers
Classifier: Operating System :: OS Independent
